pydiverse/.gitignore
pydiverse/pipedag/__init__.py
pydiverse/pipedag/_typing.py
pydiverse/pipedag/backend/__init__.py
pydiverse/pipedag/backend/blob.py
pydiverse/pipedag/backend/lock/__init__.py
pydiverse/pipedag/backend/lock/base.py
pydiverse/pipedag/backend/lock/database.py
pydiverse/pipedag/backend/lock/filelock.py
pydiverse/pipedag/backend/lock/nolock.py
pydiverse/pipedag/backend/lock/zookeeper.py
pydiverse/pipedag/backend/table/__init__.py
pydiverse/pipedag/backend/table/dict.py
pydiverse/pipedag/backend/table/cache/__init__.py
pydiverse/pipedag/backend/table/cache/parquet.py
pydiverse/pipedag/backend/table/parquet/__init__.py
pydiverse/pipedag/backend/table/sql/__init__.py
pydiverse/pipedag/backend/table/sql/ddl.py
pydiverse/pipedag/backend/table/sql/hooks.py
pydiverse/pipedag/backend/table/sql/reflection.py
pydiverse/pipedag/backend/table/sql/sql.py
pydiverse/pipedag/backend/table/sql/dialects/__init__.py
pydiverse/pipedag/backend/table/sql/dialects/duckdb.py
pydiverse/pipedag/backend/table/sql/dialects/duckdb_parquet.py
pydiverse/pipedag/backend/table/sql/dialects/ibm_db2.py
pydiverse/pipedag/backend/table/sql/dialects/mssql.py
pydiverse/pipedag/backend/table/sql/dialects/postgres.py
pydiverse/pipedag/backend/table/sql/dialects/snowflake.py
pydiverse/pipedag/container/__init__.py
pydiverse/pipedag/context/__init__.py
pydiverse/pipedag/context/context.py
pydiverse/pipedag/context/run_context.py
pydiverse/pipedag/context/trace_hook.py
pydiverse/pipedag/core/__init__.py
pydiverse/pipedag/core/config.py
pydiverse/pipedag/core/flow.py
pydiverse/pipedag/core/group_node.py
pydiverse/pipedag/core/result.py
pydiverse/pipedag/core/stage.py
pydiverse/pipedag/core/task.py
pydiverse/pipedag/debug/__init__.py
pydiverse/pipedag/engine/__init__.py
pydiverse/pipedag/engine/base.py
pydiverse/pipedag/engine/dask.py
pydiverse/pipedag/engine/prefect.py
pydiverse/pipedag/engine/sequential.py
pydiverse/pipedag/errors/__init__.py
pydiverse/pipedag/management/__init__.py
pydiverse_pipedag-0.12.11.dist-info/METADATA
pydiverse_pipedag-0.12.11.dist-info/WHEEL
pydiverse_pipedag-0.12.11.dist-info/entry_points.txt
pydiverse_pipedag-0.12.11.dist-info/licenses/LICENSE
pydiverse_pipedag-0.12.11.dist-info/RECORD
