Metadata-Version: 2.4
Name: pydiverse-pipedag
Version: 0.12.11
Summary: A pipeline orchestration library executing tasks within one python session. It takes care of SQL table (de)materialization, caching and cache invalidation. Blob storage is supported as well for example for storing model files.
Author: QuantCo, Inc.
Author-email: Nicolas Camenisch <garnele007@gmail.com>, Finn Rudolph <finn.rudolph@t-online.de>, Nicolas Mueller <github@nicolasmueller.eu>, Martin Trautmann <windiana@users.sf.net>
License: BSD 3-Clause License
License-File: LICENSE
Classifier: Development Status :: 5 - Production/Stable
Classifier: Intended Audience :: Developers
Classifier: Intended Audience :: Science/Research
Classifier: License :: OSI Approved :: BSD License
Classifier: Programming Language :: Python :: 3
Classifier: Programming Language :: Python :: 3.11
Classifier: Programming Language :: Python :: 3.12
Classifier: Programming Language :: Python :: 3.13
Classifier: Programming Language :: Python :: 3.14
Classifier: Programming Language :: SQL
Classifier: Topic :: Database
Classifier: Topic :: Scientific/Engineering
Classifier: Topic :: Software Development
Requires-Python: <3.15.0a0,>=3.11.14
Requires-Dist: attrs<26,>=25.4.0
Requires-Dist: click<9,>=8.1.8
Requires-Dist: cryptography<47,>=45.0.7
Requires-Dist: duckdb-engine<0.16,>=0.15.0
Requires-Dist: duckdb<2,>=0.10.3
Requires-Dist: fsspec<2026,>=2025.9.0
Requires-Dist: msgpack<2,>=1.1.1
Requires-Dist: networkx<4,>=3.4
Requires-Dist: packaging<26,>=25.0
Requires-Dist: pandas<3,>=1.5.3
Requires-Dist: polars<2,>=1.2.1
Requires-Dist: pyarrow<23,>=19.0.0
Requires-Dist: pydiverse-common<0.5,>=0.4.4
Requires-Dist: pynng<0.9,>=0.8.1
Requires-Dist: pyparsing<4,>=3.2.5
Requires-Dist: python-box<8,>=7.3.2
Requires-Dist: pyyaml<7,>=6.0.3
Requires-Dist: sqlalchemy!=2.0.45,<3,>=1.4.54
Requires-Dist: structlog<26,>=25.4.0
Requires-Dist: typing-extensions<5,>=4.15.0
Requires-Dist: universal-pathlib<0.4,>=0.3.2
